questioning_machine/__init__.py
questioning_machine/githf.py
questioning_machine/machina.yaml
questioning_machine-0.0.3.dist-info/LICENSE
questioning_machine-0.0.3.dist-info/METADATA
questioning_machine-0.0.3.dist-info/WHEEL
questioning_machine-0.0.3.dist-info/top_level.txt
questioning_machine-0.0.3.dist-info/RECORD
